README.md
main.py
pyproject.toml
mindcluster.egg-info/PKG-INFO
mindcluster.egg-info/SOURCES.txt
mindcluster.egg-info/dependency_links.txt
mindcluster.egg-info/top_level.txt